aws_cdk/aws_lambda_dotnet/__init__.py
aws_cdk/aws_lambda_dotnet/py.typed
aws_cdk/aws_lambda_dotnet/_jsii/__init__.py
aws_cdk/aws_lambda_dotnet/_jsii/aws-lambda-dotnet@0.0.6.jsii.tgz
aws_cdk.aws_lambda_dotnet-0.0.6.dist-info/LICENSE
aws_cdk.aws_lambda_dotnet-0.0.6.dist-info/METADATA
aws_cdk.aws_lambda_dotnet-0.0.6.dist-info/WHEEL
aws_cdk.aws_lambda_dotnet-0.0.6.dist-info/top_level.txt
aws_cdk.aws_lambda_dotnet-0.0.6.dist-info/RECORD
